wiiki_editor/Sort.txt
wiiki_editor/__init__.py
wiiki_editor/article.py
wiiki_editor/sortstring.py
wiiki_editor/lists/listcustomtracks.py
wiiki_editor/lists/listretrosothergames.py
wiiki_editor/templates/link.py
wiiki_editor/templates/status.py
wiiki_editor-0.1.0.dist-info/METADATA
wiiki_editor-0.1.0.dist-info/WHEEL
wiiki_editor-0.1.0.dist-info/licenses/LICENSE
wiiki_editor-0.1.0.dist-info/RECORD
