Metadata-Version: 2.4
Name: wiiki-editor
Version: 0.1.0
Summary: A Python package containing useful functions and classes for editing the Custom Mario Kart Wiiki.
Project-URL: repository, https://github.com/Krummers/Wiiki-Editor
Project-URL: issues, https://github.com/Krummers/Wiiki-Editor/issues
Project-URL: releasenotes, https://github.com/Krummers/Wiiki-Editor/releases
Author-email: Krummers <krummers10@gmail.com>
License:                     GNU GENERAL PUBLIC LICENSE
License-File: LICENSE
Classifier: License :: OSI Approved :: GNU General Public License v3 (GPLv3)
Classifier: Programming Language :: Python :: 3.10
Classifier: Programming Language :: Python :: 3.11
Classifier: Programming Language :: Python :: 3.12
Requires-Python: >=3.10
Requires-Dist: mwclient
